MANIFEST.in
setup.py
_newio/__init__.py
_newio/version.txt
newio_kernel/__init__.py
newio_kernel/asyncio_executor.py
newio_kernel/engine.py
newio_kernel/executor.py
newio_kernel/helper.py
newio_kernel/kernel.py
newio_kernel/kernel_api.py
newio_kernel/lounge.py
newio_kernel/selector.py
newio_kernel/timer.py
newio_kernel.egg-info/PKG-INFO
newio_kernel.egg-info/SOURCES.txt
newio_kernel.egg-info/dependency_links.txt
newio_kernel.egg-info/requires.txt
newio_kernel.egg-info/top_level.txt
newio_kernel/monitor/__init__.py
newio_kernel/monitor/__main__.py
newio_kernel/monitor/client.py
newio_kernel/monitor/server.py
newio_kernel/monitor/shell.py
tools/requires-newio-kernel.txt